<?xml version="1.0" encoding="UTF-8" standalone="yes"?>
<Lexicon_Entry Id="000568000000000" Lemma="אָסְנַת" Version="5" HasAramaic="false" InLXX="false" AlphaPos="א">
  <StrongCodes>
    <Strong>H0621</Strong>
  </StrongCodes>
  <Authors>
    <Author>Reinier de Blois</Author>
  </Authors>
  <Contributors/>
  <AlternateLemmas/>
  <MainLinks/>
  <Notes/>
  <ContributorNote/>
  <BaseForms>
    <BaseForm Id="000568001000000">
      <PartsOfSpeech>
        <PartOfSpeech/>
      </PartsOfSpeech>
      <BaseFormLinks/>
      <LEXMeanings>
        <LEXMeaning Id="000568001001000" IsBiblicalTerm="Y" EntryCode="" Indent="0">
          <LEXDomains>
            <LEXDomain Code="003001007"/>
          </LEXDomains>
          <LEXSenses>
            <LEXSense LanguageCode="en" LastEdited="2015-08-23 15:53:00" LastEditedBy="">
              <DefinitionLong/>
              <DefinitionShort/>
              <Glosses>
                <Gloss/>
              </Glosses>
              <Comments/>
            </LEXSense>
          </LEXSenses>
          <LEXReferences>
            <LEXReference>00104104500022</LEXReference>
            <LEXReference>00104105000032</LEXReference>
            <LEXReference>00104602000022</LEXReference>
          </LEXReferences>
          <LEXVideos/>
        </LEXMeaning>
      </LEXMeanings>
    </BaseForm>
  </BaseForms>
</Lexicon_Entry>
