<?xml version="1.0" encoding="UTF-8" standalone="yes"?>
<Lexicon_Entry Id="002532000000000" Lemma="חַרְטֹּם" Version="5" HasAramaic InLXX="false" AlphaPos="ח">
  <StrongCodes>
    <Strong>A2749</Strong>
  </StrongCodes>
  <Authors>
    <Author>Reinier de Blois</Author>
  </Authors>
  <Contributors/>
  <AlternateLemmas/>
  <MainLinks/>
  <Notes/>
  <ContributorNote/>
  <BaseForms>
    <BaseForm Id="002532001000000">
      <PartsOfSpeech>
        <PartOfSpeech/>
      </PartsOfSpeech>
      <BaseFormLinks/>
      <LEXMeanings>
        <LEXMeaning Id="002532001001000" IsBiblicalTerm="M" EntryCode="" Indent="0">
          <LEXDomains>
            <LEXDomain Code="001001002003009" Source="Divination" SourceCode="002003003008"/>
          </LEXDomains>
          <LEXSenses>
            <LEXSense LanguageCode="en" LastEdited="2015-09-02 16:14:52" LastEditedBy="">
              <DefinitionLong/>
              <DefinitionShort/>
              <Glosses>
                <Gloss/>
              </Glosses>
              <Comments/>
            </LEXSense>
          </LEXSenses>
          <LEXReferences>
            <LEXReference>02700201000070</LEXReference>
            <LEXReference>02700202700028</LEXReference>
            <LEXReference>02700400400010</LEXReference>
            <LEXReference>02700400600006</LEXReference>
            <LEXReference>02700501100058</LEXReference>
          </LEXReferences>
          <LEXVideos/>
          <LEXCoreDomains>
            <LEXCoreDomain Code="200"/>
            <LEXCoreDomain Code="132"/>
            <LEXCoreDomain Code="104"/>
          </LEXCoreDomains>
        </LEXMeaning>
      </LEXMeanings>
    </BaseForm>
  </BaseForms>
</Lexicon_Entry>
