<?xml version="1.0" encoding="UTF-8" standalone="yes"?>
<Lexicon_Entry Id="003906000000000" Lemma="מחק" Version="3" HasAramaic="false" InLXX="false" AlphaPos="מ">
  <StrongCodes>
    <Strong>H4277</Strong>
  </StrongCodes>
  <Authors>
    <Author>Reinier de Blois</Author>
  </Authors>
  <Contributors/>
  <AlternateLemmas/>
  <MainLinks/>
  <Notes/>
  <ContributorNote/>
  <BaseForms>
    <BaseForm Id="003906001000000">
      <PartsOfSpeech>
        <PartOfSpeech/>
      </PartsOfSpeech>
      <BaseFormLinks/>
      <LEXMeanings>
        <LEXMeaning Id="003906001001000" IsBiblicalTerm="Y" EntryCode="" Indent="0">
          <LEXDomains>
            <LEXDomain Code="002001001023"/>
          </LEXDomains>
          <LEXForms>
            <LEXForm>vbqal-</LEXForm>
          </LEXForms>
          <LEXSynonyms>
            <LEXSynonym>מחץ</LEXSynonym>
          </LEXSynonyms>
          <LEXSenses>
            <LEXSense LanguageCode="en" LastEdited="2017-12-19 13:03:17" LastEditedBy="">
              <DefinitionLong/>
              <DefinitionShort/>
              <Glosses>
                <Gloss/>
              </Glosses>
              <Comments/>
            </LEXSense>
          </LEXSenses>
          <LEXReferences>
            <LEXReference>00700502600028</LEXReference>
          </LEXReferences>
          <LEXVideos/>
          <LEXCoreDomains>
            <LEXCoreDomain Code="006"/>
          </LEXCoreDomains>
        </LEXMeaning>
      </LEXMeanings>
    </BaseForm>
  </BaseForms>
</Lexicon_Entry>
