<?xml version="1.0" encoding="UTF-8" standalone="yes"?>
<Lexicon_Entry Id="004094000000000" Lemma="מִמְשָׁק" Version="3" HasAramaic="false" InLXX="false" AlphaPos="מ">
  <StrongCodes>
    <Strong>H4476</Strong>
  </StrongCodes>
  <Authors>
    <Author>Reinier de Blois</Author>
  </Authors>
  <Contributors/>
  <AlternateLemmas/>
  <MainLinks/>
  <Notes>
    <Note Caller="1" LanguageCode="en" LastEdited="" LastEditedBy="">
      <References>
        <Reference>03600200900038</Reference>
      </References>
      <Content>RSV NRSV ESV &quot;possessed by&quot; NIV &quot;place of&quot; NJB &quot;realm of&quot; NJPS &quot;clumps&quot; REB &quot;mass of&quot; GNT &quot;overgrown with&quot; CEV &quot;covered with&quot;</Content>
    </Note>
  </Notes>
  <ContributorNote/>
  <BaseForms>
    <BaseForm Id="004094001000000">
      <PartsOfSpeech>
        <PartOfSpeech/>
      </PartsOfSpeech>
      <RelatedLemmas>
        <RelatedLemma>
          <Word>מֶשֶׁק</Word>
        </RelatedLemma>
      </RelatedLemmas>
      <BaseFormLinks/>
      <LEXMeanings>
        <LEXMeaning Id="004094001001000" IsBiblicalTerm="Y" EntryCode="" Indent="0">
          <LEXDomains>
            <LEXDomain Code="002003002008"/>
            <LEXDomain Code="002001001042"/>
          </LEXDomains>
          <LEXSenses>
            <LEXSense LanguageCode="en" LastEdited="2016-12-12 00:49:11" LastEditedBy="">
              <DefinitionLong/>
              <DefinitionShort/>
              <Glosses>
                <Gloss/>
              </Glosses>
              <Comments/>
            </LEXSense>
          </LEXSenses>
          <LEXReferences>
            <LEXReference>03600200900038{N:001}</LEXReference>
          </LEXReferences>
          <LEXVideos/>
          <LEXCoreDomains>
            <LEXCoreDomain Code="125"/>
          </LEXCoreDomains>
        </LEXMeaning>
      </LEXMeanings>
    </BaseForm>
  </BaseForms>
</Lexicon_Entry>
