<?xml version="1.0" encoding="UTF-8" standalone="yes"?>
<Lexicon_Entry Id="004702000000000" Lemma="נוף" Version="4" HasAramaic="false" InLXX="false" AlphaPos="נ">
  <StrongCodes>
    <Strong>H5130</Strong>
  </StrongCodes>
  <Authors>
    <Author>Reinier de Blois</Author>
  </Authors>
  <Contributors/>
  <AlternateLemmas/>
  <MainLinks/>
  <Notes>
    <Note Caller="1" LanguageCode="en" LastEdited="" LastEditedBy="">
      <References>
        <Reference>02303002800020</Reference>
      </References>
      <Content>RSV NJB NRSV ESV &quot;to sift&quot; REB &quot;sieves&quot; NIV &quot;shakes&quot; | NJPS &quot;to set (a yoke)&quot;</Content>
    </Note>
  </Notes>
  <ContributorNote/>
  <BaseForms>
    <BaseForm Id="004702001000000">
      <PartsOfSpeech>
        <PartOfSpeech/>
      </PartsOfSpeech>
      <RelatedLemmas>
        <RelatedLemma>
          <Word>נָפָה</Word>
        </RelatedLemma>
        <RelatedLemma>
          <Word>תְּנוּפָה</Word>
        </RelatedLemma>
      </RelatedLemmas>
      <BaseFormLinks/>
      <LEXMeanings>
        <LEXMeaning Id="004702001001000" IsBiblicalTerm="M" EntryCode="" Indent="0">
          <LEXDomains>
            <LEXDomain Code="002003002022" Source="Move" SourceCode="002002001011"/>
          </LEXDomains>
          <LEXForms>
            <LEXForm>vbhif-</LEXForm>
            <LEXForm>vbhof- (passive)</LEXForm>
          </LEXForms>
          <LEXSenses>
            <LEXSense LanguageCode="en" LastEdited="2017-11-07 11:49:58" LastEditedBy="">
              <DefinitionLong/>
              <DefinitionShort/>
              <Glosses>
                <Gloss/>
                <Gloss/>
              </Glosses>
              <Comments/>
            </LEXSense>
          </LEXSenses>
          <LEXReferences>
            <LEXReference>00202902400026</LEXReference>
            <LEXReference>00202902600028</LEXReference>
            <LEXReference>00202902700026</LEXReference>
            <LEXReference>00203502200052</LEXReference>
            <LEXReference>00300703000034</LEXReference>
            <LEXReference>00300802700028</LEXReference>
            <LEXReference>00300802900016</LEXReference>
            <LEXReference>00300902100020</LEXReference>
            <LEXReference>00301001500028</LEXReference>
            <LEXReference>00301401200042</LEXReference>
            <LEXReference>00301402400030</LEXReference>
            <LEXReference>00302301100004</LEXReference>
            <LEXReference>00302301100030</LEXReference>
            <LEXReference>00302301200010</LEXReference>
            <LEXReference>00302302000004</LEXReference>
            <LEXReference>00400502500028</LEXReference>
            <LEXReference>00400602000004</LEXReference>
            <LEXReference>00400801100004</LEXReference>
            <LEXReference>00400801300028</LEXReference>
            <LEXReference>00400801500032</LEXReference>
            <LEXReference>00400802100018</LEXReference>
          </LEXReferences>
          <LEXVideos/>
          <LEXCoreDomains>
            <LEXCoreDomain Code="110"/>
            <LEXCoreDomain Code="149"/>
          </LEXCoreDomains>
        </LEXMeaning>
        <LEXMeaning Id="004702001002000" IsBiblicalTerm="Y" EntryCode="" Indent="0">
          <LEXDomains>
            <LEXDomain Code="002003001010" Source="Move" SourceCode="002002001011"/>
          </LEXDomains>
          <LEXForms>
            <LEXForm>vbhif-</LEXForm>
          </LEXForms>
          <LEXSenses>
            <LEXSense LanguageCode="en" LastEdited="2023-01-24 20:25:56" LastEditedBy="">
              <DefinitionLong/>
              <DefinitionShort/>
              <Glosses>
                <Gloss/>
                <Gloss/>
              </Glosses>
              <Comments/>
            </LEXSense>
          </LEXSenses>
          <LEXReferences>
            <LEXReference>00202002500026</LEXReference>
            <LEXReference>00502302600028</LEXReference>
            <LEXReference>00502700500022</LEXReference>
            <LEXReference>00600803100044</LEXReference>
            <LEXReference>02301001500028</LEXReference>
            <LEXReference>02301001500032</LEXReference>
          </LEXReferences>
          <LEXVideos/>
          <LEXCoreDomains>
            <LEXCoreDomain Code="019"/>
            <LEXCoreDomain Code="027"/>
          </LEXCoreDomains>
        </LEXMeaning>
        <LEXMeaning Id="004702001003000" IsBiblicalTerm="M" EntryCode="" Indent="1">
          <LEXDomains>
            <LEXDomain Code="002003002002" Source="Hold" SourceCode="002003001010"/>
          </LEXDomains>
          <LEXForms>
            <LEXForm>vbhif-</LEXForm>
          </LEXForms>
          <LEXSenses>
            <LEXSense LanguageCode="en" LastEdited="2017-11-07 11:49:58" LastEditedBy="">
              <DefinitionLong/>
              <DefinitionShort/>
              <Glosses>
                <Gloss/>
                <Gloss/>
              </Glosses>
              <Comments/>
            </LEXSense>
          </LEXSenses>
          <LEXReferences>
            <LEXReference>02303002800020{N:001}</LEXReference>
          </LEXReferences>
          <LEXLinks>
            <LEXLink>Realia:1.1.8.4</LEXLink>
          </LEXLinks>
          <LEXVideos/>
          <LEXCoreDomains>
            <LEXCoreDomain Code="055"/>
            <LEXCoreDomain Code="140"/>
          </LEXCoreDomains>
        </LEXMeaning>
        <LEXMeaning Id="004702001004000" IsBiblicalTerm="Y" EntryCode="" Indent="0">
          <LEXDomains>
            <LEXDomain Code="002001001058" Source="Move" SourceCode="002002001011"/>
          </LEXDomains>
          <LEXCollocations>
            <LEXCollocation>הֵנִיף יָד</LEXCollocation>
          </LEXCollocations>
          <LEXSenses>
            <LEXSense LanguageCode="en" LastEdited="2023-01-24 20:25:56" LastEditedBy="">
              <DefinitionLong/>
              <DefinitionShort/>
              <Glosses>
                <Gloss/>
              </Glosses>
              <Comments/>
            </LEXSense>
          </LEXSenses>
          <LEXReferences>
            <LEXReference>01200501100044</LEXReference>
            <LEXReference>01803102100004</LEXReference>
            <LEXReference>02301003200016</LEXReference>
            <LEXReference>02301101500018</LEXReference>
            <LEXReference>02301300200018</LEXReference>
            <LEXReference>02301901600046</LEXReference>
            <LEXReference>03800201300006</LEXReference>
          </LEXReferences>
          <LEXVideos/>
          <LEXCoreDomains>
            <LEXCoreDomain Code="019"/>
          </LEXCoreDomains>
        </LEXMeaning>
        <LEXMeaning Id="004702001005000" IsBiblicalTerm="X" EntryCode="" Indent="0">
          <LEXSenses>
            <LEXSense LanguageCode="en" LastEdited="" LastEditedBy="">
              <DefinitionLong/>
              <DefinitionShort/>
              <Glosses>
                <Gloss/>
              </Glosses>
              <Comments/>
            </LEXSense>
          </LEXSenses>
          <LEXReferences>
            <LEXReference>02303002800020</LEXReference>
          </LEXReferences>
          <LEXVideos/>
        </LEXMeaning>
      </LEXMeanings>
    </BaseForm>
    <BaseForm Id="004702002000000">
      <PartsOfSpeech>
        <PartOfSpeech/>
      </PartsOfSpeech>
      <RelatedLemmas>
        <RelatedLemma>
          <Word>נֹפֶת</Word>
        </RelatedLemma>
      </RelatedLemmas>
      <BaseFormLinks/>
      <LEXMeanings>
        <LEXMeaning Id="004702002001000" IsBiblicalTerm="Y" EntryCode="" Indent="0">
          <LEXDomains>
            <LEXDomain Code="002003002023"/>
          </LEXDomains>
          <LEXForms>
            <LEXForm>vbqal-</LEXForm>
          </LEXForms>
          <LEXSenses>
            <LEXSense LanguageCode="en" LastEdited="2017-08-23 20:43:13" LastEditedBy="">
              <DefinitionLong/>
              <DefinitionShort/>
              <Glosses>
                <Gloss/>
                <Gloss/>
              </Glosses>
              <Comments/>
            </LEXSense>
          </LEXSenses>
          <LEXReferences>
            <LEXReference>02000701700002</LEXReference>
          </LEXReferences>
          <LEXVideos/>
          <LEXCoreDomains>
            <LEXCoreDomain Code="166"/>
            <LEXCoreDomain Code="082"/>
          </LEXCoreDomains>
        </LEXMeaning>
        <LEXMeaning Id="004702002002000" IsBiblicalTerm="Y" EntryCode="" Indent="0">
          <LEXDomains>
            <LEXDomain Code="002003002023"/>
          </LEXDomains>
          <LEXForms>
            <LEXForm>vbhif-</LEXForm>
          </LEXForms>
          <LEXSenses>
            <LEXSense LanguageCode="en" LastEdited="2017-11-07 11:49:58" LastEditedBy="">
              <DefinitionLong/>
              <DefinitionShort/>
              <Glosses>
                <Gloss/>
              </Glosses>
              <Comments/>
            </LEXSense>
          </LEXSenses>
          <LEXReferences>
            <LEXReference>01906801000006</LEXReference>
          </LEXReferences>
          <LEXVideos/>
          <LEXCoreDomains>
            <LEXCoreDomain Code="166"/>
            <LEXCoreDomain Code="193"/>
            <LEXCoreDomain Code="055"/>
          </LEXCoreDomains>
        </LEXMeaning>
      </LEXMeanings>
    </BaseForm>
  </BaseForms>
</Lexicon_Entry>
