<?xml version="1.0" encoding="UTF-8" standalone="yes"?>
<Lexicon_Entry Id="005734000000000" Lemma="עַשְׁתָּרֹת" Version="5" HasAramaic="false" InLXX="false" AlphaPos="ע">
  <StrongCodes>
    <Strong>H6252</Strong>
  </StrongCodes>
  <Authors>
    <Author>Reinier de Blois</Author>
  </Authors>
  <Contributors/>
  <AlternateLemmas>
    <AlternateLemma>עַשְׁתָּרֹות</AlternateLemma>
  </AlternateLemmas>
  <MainLinks/>
  <Notes/>
  <ContributorNote/>
  <BaseForms>
    <BaseForm Id="005734001000000">
      <PartsOfSpeech>
        <PartOfSpeech/>
      </PartsOfSpeech>
      <RelatedNames>
        <RelatedName>
          <Word>עַשְׁתֹּרֶת</Word>
        </RelatedName>
        <RelatedName>
          <Word>עַשְׁתְּרָתִי</Word>
        </RelatedName>
      </RelatedNames>
      <BaseFormLinks/>
      <LEXMeanings>
        <LEXMeaning Id="005734001001000" IsBiblicalTerm="Y" EntryCode="" Indent="0">
          <LEXDomains>
            <LEXDomain Code="003001010"/>
          </LEXDomains>
          <LEXSenses>
            <LEXSense LanguageCode="en" LastEdited="2015-11-16 23:20:33" LastEditedBy="">
              <DefinitionLong/>
              <DefinitionShort/>
              <Glosses>
                <Gloss/>
              </Glosses>
              <Comments/>
            </LEXSense>
          </LEXSenses>
          <LEXReferences>
            <LEXReference>00500100400042</LEXReference>
            <LEXReference>00600901000056</LEXReference>
            <LEXReference>00601200400028</LEXReference>
            <LEXReference>00601301200020</LEXReference>
            <LEXReference>00601303100012</LEXReference>
            <LEXReference>01300605600038</LEXReference>
          </LEXReferences>
          <LEXVideos/>
          <LEXCoordinates>
            <LEXCoordinates>32.833333,36.016666</LEXCoordinates>
          </LEXCoordinates>
        </LEXMeaning>
      </LEXMeanings>
    </BaseForm>
  </BaseForms>
</Lexicon_Entry>
