<?xml version="1.0" encoding="UTF-8" standalone="yes"?>
<Lexicon_Entry Id="000838000000000" Lemma="αὐτάρκης" Version="0" HasAramaic="false" InLXX AlphaPos="α">
  <StrongCodes>
    <Strong>G0842</Strong>
  </StrongCodes>
  <Authors/>
  <AlternateLemmas/>
  <MainLinks/>
  <Notes/>
  <ContributorNote/>
  <BaseForms>
    <BaseForm Id="000838001000000">
      <PartsOfSpeech>
        <PartOfSpeech/>
      </PartsOfSpeech>
      <Inflections>
        <Inflection Lemma="αὐτάρκης" BaseFormIndex="1">
          <Form/>
          <Realizations>
            <Realization>-ες</Realization>
          </Realizations>
          <Comments/>
        </Inflection>
      </Inflections>
      <Constructs>
        <Construct Lemma="αὐτάρκης" BaseFormIndex="1">
          <WordMeaningSet>
            <Word>αὐτός</Word>
          </WordMeaningSet>
          <WordMeaningSet>
            <Word>ἀρκέω</Word>
          </WordMeaningSet>
        </Construct>
      </Constructs>
      <BaseFormLinks/>
      <LEXMeanings>
        <LEXMeaning Id="000838001001000" IsBiblicalTerm="Y" EntryCode="25.84" Indent="0">
          <LEXDomains>
            <LEXDomain/>
          </LEXDomains>
          <LEXSubDomains>
            <LEXSubDomain/>
          </LEXSubDomains>
          <LEXSenses>
            <LEXSense LanguageCode="en" LastEdited="2021-08-18 14:48:03" LastEditedBy="">
              <DefinitionLong/>
              <DefinitionShort/>
              <Glosses>
                <Gloss/>
                <Gloss/>
              </Glosses>
              <Comments/>
            </LEXSense>
          </LEXSenses>
          <LEXReferences>
            <LEXReference>05000401100024</LEXReference>
          </LEXReferences>
          <LEXVideos/>
        </LEXMeaning>
      </LEXMeanings>
    </BaseForm>
  </BaseForms>
</Lexicon_Entry>
