<?xml version="1.0" encoding="UTF-8" standalone="yes"?>
<Lexicon_Entry Id="001503000000000" Lemma="Ἑζεκίας" Version="0" HasAramaic="false" InLXX="false" AlphaPos="ε">
  <StrongCodes>
    <Strong>G1478</Strong>
  </StrongCodes>
  <Authors/>
  <AlternateLemmas/>
  <MainLinks/>
  <Notes/>
  <ContributorNote/>
  <BaseForms>
    <BaseForm Id="001503001000000">
      <PartsOfSpeech>
        <PartOfSpeech/>
      </PartsOfSpeech>
      <Inflections>
        <Inflection Lemma="Ἑζεκίας" BaseFormIndex="1">
          <Form/>
          <Realizations>
            <Realization>-ου</Realization>
          </Realizations>
          <Comments/>
        </Inflection>
      </Inflections>
      <BaseFormLinks/>
      <LEXMeanings>
        <LEXMeaning Id="001503001001000" IsBiblicalTerm="M" EntryCode="93.106" Indent="0">
          <LEXDomains>
            <LEXDomain/>
          </LEXDomains>
          <LEXSubDomains>
            <LEXSubDomain/>
          </LEXSubDomains>
          <LEXSenses>
            <LEXSense LanguageCode="en" LastEdited="2021-09-01 20:55:49" LastEditedBy="">
              <DefinitionLong/>
              <DefinitionShort/>
              <Glosses>
                <Gloss/>
              </Glosses>
              <Comments/>
            </LEXSense>
          </LEXSenses>
          <LEXReferences>
            <LEXReference>04000100900030</LEXReference>
            <LEXReference>04000101000002</LEXReference>
          </LEXReferences>
          <LEXVideos/>
        </LEXMeaning>
      </LEXMeanings>
    </BaseForm>
  </BaseForms>
</Lexicon_Entry>
